EMGT/OutlierFinder.py
EMGT/PlotSubjects.py
EMGT/SignalFilterer.py
EMGT/__init__.py
emgt-0.0.1.dist-info/METADATA
emgt-0.0.1.dist-info/WHEEL
emgt-0.0.1.dist-info/licenses/LICENSE
emgt-0.0.1.dist-info/RECORD
