Metadata-Version: 2.1
Name: EMGT
Version: 0.0.1
Summary: A general EMG processing and feature extraction package.
Author-email: William Conley <william@cconley.ca>
License-File: LICENSE
Classifier: License :: OSI Approved :: GNU General Public License v3 or later (GPLv3+)
Classifier: Operating System :: OS Independent
Classifier: Programming Language :: Python :: 3
Requires-Python: >=3.8
